LICENSE
MANIFEST.in
README.rst
setup.py
docs/Makefile
docs/make.bat
samples/__init__.py
samples/context.py
samples/sample1.py
samples/sample2.py
splatoon_league_corr/__init__.py
splatoon_league_corr/input_tcsv.py
splatoon_league_corr/mk_corr_list.py
splatoon_league_corr/mkxl.py
splatoon_league_corr/mylist.py
splatoon_league_corr/splatoon_league_corr.py
splatoon_league_corr/team_data.py
splatoon_league_corr.egg-info/PKG-INFO
splatoon_league_corr.egg-info/SOURCES.txt
splatoon_league_corr.egg-info/dependency_links.txt
splatoon_league_corr.egg-info/requires.txt
splatoon_league_corr.egg-info/top_level.txt