Metadata-Version: 2.1
Name: splatoon-league-corr
Version: 1.0.1
Summary: Correlation Coefficient Table for Splatoon s League
Home-page: https://github.com/JmpM-0743/splatoon_league_corr.git
Author: Maruyama Jumpei
Author-email: jmp.mtywt.lv@gmail.com
License: Copyright (c) 2020, Jumpei Maruyama
Platform: UNKNOWN
